LICENSE
MANIFEST.in
README.md
setup.cfg
setup.py
datesuninfo/__init__.py
datesuninfo.egg-info/PKG-INFO
datesuninfo.egg-info/SOURCES.txt
datesuninfo.egg-info/dependency_links.txt
datesuninfo.egg-info/entry_points.txt
datesuninfo.egg-info/requires.txt
datesuninfo.egg-info/top_level.txt