Metadata-Version: 1.1
Name: datesuninfo
Version: 0.1.0
Summary: Mimics PHPs date_sun_info() using pyephem.
Home-page: https://github.com/okzach/datesuninfo/
Author: Zach Adams
Author-email: zach@okzach.com
License: MIT
Platform: UNKNOWN
Classifier: Development Status :: 3 - Alpha
Classifier: License :: OSI Approved :: MIT License
Classifier: Natural Language :: English
Classifier: Programming Language :: Python :: 2
Classifier: Programming Language :: Python :: 2.7
Classifier: Programming Language :: Python :: 3
Classifier: Programming Language :: Python :: 3.5
